src/Parameter.v
// =========================================================================
// Practical 4: StarCore-1 — Single-Cycle Processor in Verilog
// =========================================================================
//
// GROUP NUMBER: 6
//
// MEMBERS:
//   - Member 1 Michael Lighton, LGHMIC003
//   - Member 2 Glen Jones, JNSGLE007

// File        : Parameter.v
// Description : Shared compile-time parameters used across all modules.
//               Include this file at the top of every .v file:
//                   `include "../src/Parameter.v"
// =============================================================================

// Compiler guards - prevent from being inlcuded more than once during compilation
`ifndef PARAMETER_H_
`define PARAMETER_H_

// ---------------------------------------------------------------------------
// Memory dimensions
// ---------------------------------------------------------------------------
`define COL     16          // Data/instruction word width (bits)
`define ROW_I   16          // Instruction memory depth (words, 16 x 16-bit)
`define ROW_D    8          // Data memory depth (words,  8 x 16-bit)

// ---------------------------------------------------------------------------
// Simulation control
// Increase SIM_TIME if your test program needs more clock cycles to complete.
// At 10 ns per clock (100 MHz) each #10 is one half-period; 320 ns = 16 cycles.
// ---------------------------------------------------------------------------
`define SIM_TIME #640      // 640 - 100000 Total simulation time for integration testbench

// ---------------------------------------------------------------------------
// Output file for data-memory dump (used in DataMemory.v $fmonitor)
// ---------------------------------------------------------------------------
`define DMEM_LOG  "./waves/dmem_log.txt"

`endif  // PARAMETER_H_

src/DataMemory.v
// =========================================================================
// Practical 4: StarCore-1 — Single-Cycle Processor in Verilog
// =========================================================================
//
// GROUP NUMBER: 6
//
// MEMBERS:
//   - Member 1 Michael Lighton, LGHMIC003
//   - Member 2 Glen Jones, JNSGLE007

// File        : DataMemory.v
// Description : Data Memory (RAM).
//               8 words × 16 bits. Contents loaded at simulation start from
//               the binary file ./test/test.data using $readmemb.
//               Writes are synchronous (positive-edge clocked).
//               Reads are combinational and gated by the mem_read enable.
//
// Task 4 — Student Implementation Required
// =============================================================================

`timescale 1ns / 1ps
`include "../src/Parameter.v"

module DataMemory (
    input        clk,

    // Shared address bus (used for both reads and writes)
    input  [15:0] mem_access_addr,  // Byte address; only lower bits used for indexing

    // Write port
    input  [15:0] mem_write_data,   // Data to store
    input        mem_write_en,      // Assert to write on the next posedge clk

    // Read port
    input        mem_read,          // Assert to enable the read output
    output [15:0] mem_read_data     // Read result; 16'd0 when mem_read is de-asserted
);

    // -------------------------------------------------------------------------
    // TODO: Declare the data memory array.
    //       It should hold `ROW_D entries, each `COL bits wide.
    //
    //       reg [`COL-1:0] memory [`ROW_D-1:0];
    // -------------------------------------------------------------------------
    reg [`COL-1:0] memory [`ROW_D-1:0]; // Data memory array: 16 entries, each 16 bits wide (defined in Parameter.v)


    // -------------------------------------------------------------------------
    // TODO: Derive the word address from mem_access_addr.
    //       The data memory is 8 words deep so only 3 address bits are needed.
    //       The ALU computes a byte address; use the lower 3 bits as the index:
    //
    //           wire [2:0] ram_addr = mem_access_addr[2:0];
    //
    //       This maps byte addresses 0,1,2,3,4,5,6,7 to words 0–7.
    //       (In a full system the byte offset within a word would also be
    //       handled, but StarCore-1 only supports 16-bit aligned accesses.)
    // -------------------------------------------------------------------------
    wire [2:0] ram_addr = mem_access_addr[2:0]; // Maps byte address to word index for data memory

    // -------------------------------------------------------------------------
    // TODO: Load the data memory from file at simulation start.
    //       The file ./test/test.data must contain one 16-bit binary value
    //       per line (8 lines total, one per word).
    //
    //       integer log_fd;
    //       initial begin
    //           $readmemb("./test/test.data", memory);
    //       end
    //
    //       Optional — add a $fmonitor to log memory contents to a file.
    //       This is useful for verifying ST instructions during simulation:
    //
    //       initial begin
    //           log_fd = $fopen(`DMEM_LOG);
    //           $fmonitor(log_fd, "t=%0t  [0]=%h [1]=%h [2]=%h [3]=%h",
    //                     $time, memory[0], memory[1], memory[2], memory[3]);
    //           `SIM_TIME;
    //           $fclose(log_fd);
    //       end
    // -------------------------------------------------------------------------
    integer log_fd; // File descriptor for logging memory contents
    initial begin
        $readmemb("./test.data", memory); // Load data memory contents from file
        log_fd = $fopen(`DMEM_LOG); // Open log file for writing
        $fmonitor(log_fd, "t=%0t  [0]=%h [1]=%h [2]=%h [3]=%h",
                  $time, memory[0], memory[1], memory[2], memory[3]); // Log memory contents on every change
        `SIM_TIME; // Run simulation for specified time
        $fclose(log_fd); // Close log file at the end of simulation
    end


    // -------------------------------------------------------------------------
    // TODO: Implement the synchronous write port.
    //       Write mem_write_data to memory[ram_addr] on the rising clock edge
    //       when mem_write_en is asserted.
    //
    //       always @(posedge clk) begin
    //           if (mem_write_en)
    //               memory[ram_addr] <= mem_write_data;
    //       end
    //
    //       IMPORTANT: Use non-blocking assignment (<=).
    // -------------------------------------------------------------------------
    always @(posedge clk) begin // Synchronous write port: triggered on the rising edge of the clock
        if (mem_write_en) // Check if write enable is asserted
            memory[ram_addr] <= mem_write_data; // Write data to the specified memory address using non-blocking assignment
    end


    // -------------------------------------------------------------------------
    // TODO: Implement the combinational (gated) read port.
    //       When mem_read is 1, output memory[ram_addr].
    //       When mem_read is 0, output 16'd0 (prevents spurious register writes
    //       during non-LD instructions).
    //
    //       assign mem_read_data = mem_read ? memory[ram_addr] : 16'd0;
    // -------------------------------------------------------------------------
    assign mem_read_data = mem_read ? memory[ram_addr] : 16'd0; // Gated read port: output memory[ram_addr] when mem_read is asserted, otherwise 0


endmodule

tb/DataMemory_tb.v
// =============================================================================
// EEE4120F Practical 4 — StarCore-1 Processor
// File        : DataMemory_tb.v
// Description : Testbench for the Data Memory module (Task 4).
//               Verifies synchronous write, gated combinational read,
//               write followed by immediate read, and disabled-write safety.
//
// Run:
//   iverilog -Wall -I ../src -o ../build/dm_sim ../src/DataMemory.v DataMemory_tb.v
//   cd ../test && ../build/dm_sim
//   gtkwave ../waves/dm_tb.vcd &
// =============================================================================

`timescale 1ns / 1ps
`include "../src/Parameter.v"

module DataMemory_tb;

    reg        clk;
    reg  [15:0] mem_access_addr;
    reg  [15:0] mem_write_data;
    reg        mem_write_en;
    reg        mem_read;
    wire [15:0] mem_read_data;

    DataMemory uut (
        .clk             (clk),
        .mem_access_addr (mem_access_addr),
        .mem_write_data  (mem_write_data),
        .mem_write_en    (mem_write_en),
        .mem_read        (mem_read),
        .mem_read_data   (mem_read_data)
    );

    initial clk = 1'b0;
    always  #5 clk = ~clk;

    initial begin
        $dumpfile("../waves/dm_tb.vcd");
        $dumpvars(0, DataMemory_tb);
    end

    integer fail_count;
    integer test_id;
    integer i;

    initial begin
        fail_count      = 0;
        test_id         = 1;
        mem_write_en    = 1'b0;
        mem_read        = 1'b0;
        mem_access_addr = 16'd0;
        mem_write_data  = 16'd0;

        $display("=== DataMemory Testbench ===");

        // ------------------------------------------------------------------
        // TEST GROUP 1: Read back initial values loaded from test.data
        // ------------------------------------------------------------------
        $display("--- Group 1: Verify $readmemb initialisation ---");

        // TODO: Read each of the 8 memory locations and verify against
        //       the known contents of your test.data file.
        //       Remember: only mem_access_addr[2:0] is used as the index.
        //       Address 16'd0 -> word 0, address 16'd2 -> word 2, etc.
        //       (Or use address 16'd0 -> word 0, address 16'd1 -> word 1,
        //        since only the lower 3 bits matter.)
        //
        //       mem_read = 1'b1;
        //       mem_access_addr = 16'd0; #5;
        //       if (mem_read_data !== 16'h0001)  // expected value from test.data line 0
        //           $display("FAIL [T%0d]: addr=0 got=0x%h exp=0x0001", test_id, mem_read_data);
        //       else
        //           $display("PASS [T%0d]", test_id);
        //       test_id = test_id + 1;

            for(i = 0; i < 8 ; i=i+1) begin
                // set contorl signal and addrs
                mem_read = 1'b1;
                mem_access_addr = i[15:0];
                #5;

                // Check result contains 16'h0001 for all entries
                if (mem_read_data !== (i + 16'h0001)) begin
                    $display("FAIL [T%0d]: addr=0 got=0x%h exp=0x%h", test_id, mem_read_data, (16'h0001));
                    fail_count = fail_count + 1;
                end
                else begin
                   $display("PASS [T%0d]", test_id);
               end

               test_id = test_id + 1;
            end




        // ------------------------------------------------------------------
        // TEST GROUP 2: Write new values to all 8 locations, then read back
        // ------------------------------------------------------------------
        $display("--- Group 2: Write then read all 8 locations ---");

        // TODO: Write a distinct value to each of the 8 addresses using
        //       mem_write_en and posedge clk, then read each back.
        //
        //       // Write to address 0
        //       mem_write_en    = 1'b1;
        //       mem_access_addr = 16'd0;
        //       mem_write_data  = 16'hABCD;
        //       @(posedge clk); #1;
        //       mem_write_en    = 1'b0;
        //
        //       // Read back from address 0
        //       mem_read = 1'b1;
        //       mem_access_addr = 16'd0; #5;
        //       if (mem_read_data !== 16'hABCD) ...
        //       test_id = test_id + 1;

        // Writing Values
        for (i=0; i < 8; i = i + 1) begin
            mem_read        = 1'b0; // DEassign
            mem_write_en    = 1'b1;
            mem_access_addr = i[15:0];
            mem_write_data  = i[15:0] + 16'hABCD; // Distinct value for each cell

            @(posedge clk); #1;
        end
        
        mem_write_en = 1'b0; // Turn off write enable after writing

    // Read and verify
        for (i=0; i<8; i = i + 1) begin
            mem_read = 1'b1;
            mem_access_addr = i[15:0];
            #5; // wait for readout

            if (mem_read_data !== (i[15:0] + 16'hABCD)) begin
                $display("FAIL [T%0d]: Write/Read addr=%0d got=0x%h exp=0x%h", 
                          test_id, i, mem_read_data, (i + 16'hABCD));
                fail_count = fail_count + 1;
            end else begin
                $display("PASS [T%0d]", test_id);
            end
            test_id = test_id + 1;

        end





        // ------------------------------------------------------------------
        // TEST GROUP 3: mem_read = 0 must produce 16'd0 output
        // ------------------------------------------------------------------
        $display("--- Group 3: mem_read disabled -> output must be 0 ---");

        // TODO: De-assert mem_read and verify the output is 16'd0 regardless
        //       of the address.
        //
        //       mem_read = 1'b0;
        //       mem_access_addr = 16'd0; #5;
        //       if (mem_read_data !== 16'd0)
        //           $display("FAIL [T%0d]: mem_read=0 but output=%h", test_id, mem_read_data);
        //       else
        //           $display("PASS [T%0d]: output = 0 when mem_read=0", test_id);
        //       test_id = test_id + 1;


        for (i = 0; i <8; i = i + 1) begin
            mem_read = 1'b0;
            mem_write_en = 1'b0;
            mem_access_addr = i[15:0];
            #5;

            // Verify output zero
            if (mem_read_data !== 16'd0) begin
               $display("FAIL [T%0d]: mem_read=0 but output=%h", test_id, mem_read_data);
               fail_count = fail_count + 1;
            end else begin
              $display("PASS [T%0d]: output = 0 when mem_read=0", test_id);
            end

           test_id = test_id + 1;

        end

        // ------------------------------------------------------------------
        // TEST GROUP 4: Write then immediately read on the next cycle
        // ------------------------------------------------------------------
        $display("--- Group 4: Write followed by immediate read ---");

        // TODO: Write to address 3, then on the very next cycle read back
        //       from address 3 and confirm the new value is returned.

        // Writing data
        mem_read = 1'b0;
        mem_write_en = 1'b1;
        mem_access_addr = 16'd3;
        mem_write_data = 16'hB00B;

        // TRigger setup Read signals
        @(posedge clk)
        #1;     // small delay

        // Immediately read sifgnals
        mem_write_en = 1'b0;
        mem_read = 1'b1;
        mem_access_addr = 3'd3;
        #5; // wait for combinational logic output

        // Verify
        if (mem_read_data !== 16'hB00B) begin 
            $display("FAIL [T%0d]: RAW Test address = 3, got 0x%h exp = 0xB00B", test_id,mem_read_data);
            fail_count = fail_count + 1;
        end else begin  
            $display("PASS [T%0d]", test_id);
        end
        test_id = test_id + 1;

        // ------------------------------------------------------------------
        // TEST GROUP 5: Disabled write must not alter memory
        // ------------------------------------------------------------------
        $display("--- Group 5: mem_write_en=0 must not overwrite memory ---");

        // TODO: Assert mem_write_en=0, clock one cycle, then read and confirm
        //       the previous value is unchanged.


        // Didnt specify for which, so doing all
        for(i = 0; i < 8; i = i + 1)begin
            // Try write whith write disabled
            mem_write_en = 1'b0;
            mem_access_addr = i[15:0];
            mem_write_data = 16'hABBA;

            @(posedge clk);
            #1;

            if (mem_read_data == 16'hABBA) begin
                $display("FAIL [T%0d]: Disabled write failed at addr=%0d", test_id, i);
                fail_count = fail_count + 1;
            end else begin
                $display("PASS [T%0d]: addr=%0d no write protected", test_id, i);
            end
        
            test_id = test_id + 1;
        end


        $display("");
        if (fail_count == 0)
            $display("=== ALL %0d TESTS PASSED ===", test_id - 1);
        else
            $display("=== %0d / %0d TESTS FAILED ===", fail_count, test_id - 1);
        $finish;
    end

endmodule

waves/dm_tb.vcd
$date
	Wed Apr 22 11:20:21 2026
$end
$version
	Icarus Verilog
$end
$timescale
	1ps
$end
$scope module DataMemory_tb $end
$var wire 16 ! mem_read_data [15:0] $end
$var reg 1 " clk $end
$var reg 16 # mem_access_addr [15:0] $end
$var reg 1 $ mem_read $end
$var reg 16 % mem_write_data [15:0] $end
$var reg 1 & mem_write_en $end
$var integer 32 ' fail_count [31:0] $end
$var integer 32 ( i [31:0] $end
$var integer 32 ) test_id [31:0] $end
$scope module uut $end
$var wire 1 " clk $end
$var wire 16 * mem_access_addr [15:0] $end
$var wire 1 $ mem_read $end
$var wire 16 + mem_write_data [15:0] $end
$var wire 1 & mem_write_en $end
$var wire 3 , ram_addr [2:0] $end
$var wire 16 - mem_read_data [15:0] $end
$var integer 32 . log_fd [31:0] $end
$upscope $end
$upscope $end
$enddefinitions $end
$comment Show the parameter values. $end
$dumpall
$end
#0
$dumpvars
b0 .
b1 -
b0 ,
b0 +
b0 *
b1 )
b0 (
b0 '
0&
b0 %
1$
b0 #
0"
b1 !
$end
#5000
b10 !
b10 -
b1 ,
b1 #
b1 *
b1 (
b10 )
1"
#10000
b11 !
b11 -
b10 ,
b10 #
b10 *
b10 (
b11 )
0"
#15000
b100 !
b100 -
b11 ,
b11 #
b11 *
b11 (
b100 )
1"
#20000
b101 !
b101 -
b100 ,
b100 #
b100 *
b100 (
b101 )
0"
#25000
b110 !
b110 -
b101 ,
b101 #
b101 *
b101 (
b110 )
1"
#30000
b111 !
b111 -
b110 ,
b110 #
b110 *
b110 (
b111 )
0"
#35000
b1000 !
b1000 -
b111 ,
b111 #
b111 *
b111 (
b1000 )
1"
#40000
b0 ,
b0 !
b0 -
b1010101111001101 %
b1010101111001101 +
b0 #
b0 *
1&
0$
b0 (
b1001 )
0"
#45000
1"
#46000
b1 ,
b1010101111001110 %
b1010101111001110 +
b1 #
b1 *
b1 (
#50000
0"
#55000
1"
#56000
b10 ,
b1010101111001111 %
b1010101111001111 +
b10 #
b10 *
b10 (
#60000
0"
#65000
1"
#66000
b11 ,
b1010101111010000 %
b1010101111010000 +
b11 #
b11 *
b11 (
#70000
0"
#75000
1"
#76000
b100 ,
b1010101111010001 %
b1010101111010001 +
b100 #
b100 *
b100 (
#80000
0"
#85000
1"
#86000
b101 ,
b1010101111010010 %
b1010101111010010 +
b101 #
b101 *
b101 (
#90000
0"
#95000
1"
#96000
b110 ,
b1010101111010011 %
b1010101111010011 +
b110 #
b110 *
b110 (
#100000
0"
#105000
1"
#106000
b111 ,
b1010101111010100 %
b1010101111010100 +
b111 #
b111 *
b111 (
#110000
0"
#115000
1"
#116000
b0 ,
b1010101111001101 !
b1010101111001101 -
b0 #
b0 *
1$
0&
b0 (
#120000
0"
#121000
b1010101111001110 !
b1010101111001110 -
b1 ,
b1 #
b1 *
b1 (
b1010 )
#125000
1"
#126000
b1010101111001111 !
b1010101111001111 -
b10 ,
b10 #
b10 *
b10 (
b1011 )
#130000
0"
#131000
b1010101111010000 !
b1010101111010000 -
b11 ,
b11 #
b11 *
b11 (
b1100 )
#135000
1"
#136000
b1010101111010001 !
b1010101111010001 -
b100 ,
b100 #
b100 *
b100 (
b1101 )
#140000
0"
#141000
b1010101111010010 !
b1010101111010010 -
b101 ,
b101 #
b101 *
b101 (
b1110 )
#145000
1"
#146000
b1010101111010011 !
b1010101111010011 -
b110 ,
b110 #
b110 *
b110 (
b1111 )
#150000
0"
#151000
b1010101111010100 !
b1010101111010100 -
b111 ,
b111 #
b111 *
b111 (
b10000 )
#155000
1"
#156000
b0 ,
b0 !
b0 -
b0 #
b0 *
0$
b0 (
b10001 )
#160000
0"
#161000
b1 ,
b1 #
b1 *
b1 (
b10010 )
#165000
1"
#166000
b10 ,
b10 #
b10 *
b10 (
b10011 )
#170000
0"
#171000
b11 ,
b11 #
b11 *
b11 (
b10100 )
#175000
1"
#176000
b100 ,
b100 #
b100 *
b100 (
b10101 )
#180000
0"
#181000
b101 ,
b101 #
b101 *
b101 (
b10110 )
#185000
1"
#186000
b110 ,
b110 #
b110 *
b110 (
b10111 )
#190000
0"
#191000
b111 ,
b111 #
b111 *
b111 (
b11000 )
#195000
1"
#196000
b11 ,
b1011000000001011 %
b1011000000001011 +
b11 #
b11 *
1&
b1000 (
b11001 )
#200000
0"
#205000
1"
#206000
b1011000000001011 !
b1011000000001011 -
1$
0&
#210000
0"
#211000
b1010101111001101 !
b1010101111001101 -
b0 ,
b1010101110111010 %
b1010101110111010 +
b0 #
b0 *
b0 (
b11010 )
#215000
1"
#216000
b1010101111001110 !
b1010101111001110 -
b1 ,
b1 #
b1 *
b1 (
b11011 )
#220000
0"
#225000
1"
#226000
b1010101111001111 !
b1010101111001111 -
b10 ,
b10 #
b10 *
b10 (
b11100 )
#230000
0"
#235000
1"
#236000
b1011000000001011 !
b1011000000001011 -
b11 ,
b11 #
b11 *
b11 (
b11101 )
#240000
0"
#245000
1"
#246000
b1010101111010001 !
b1010101111010001 -
b100 ,
b100 #
b100 *
b100 (
b11110 )
#250000
0"
#255000
1"
#256000
b1010101111010010 !
b1010101111010010 -
b101 ,
b101 #
b101 *
b101 (
b11111 )
#260000
0"
#265000
1"
#266000
b1010101111010011 !
b1010101111010011 -
b110 ,
b110 #
b110 *
b110 (
b100000 )
#270000
0"
#275000
1"
#276000
b1010101111010100 !
b1010101111010100 -
b111 ,
b111 #
b111 *
b111 (
b100001 )
#280000
0"
#285000
1"
#286000
b1000 (
b100010 )
