src/Parameter.v
// =========================================================================
// Practical 4: StarCore-1 — Single-Cycle Processor in Verilog
// =========================================================================
//
// GROUP NUMBER: 6
//
// MEMBERS:
//   - Member 1 Michael Lighton, LGHMIC003
//   - Member 2 Glen Jones, JNSGLE007

// File        : Parameter.v
// Description : Shared compile-time parameters used across all modules.
//               Include this file at the top of every .v file:
//                   `include "../src/Parameter.v"
// =============================================================================

// Compiler guards - prevent from being inlcuded more than once during compilation
`ifndef PARAMETER_H_
`define PARAMETER_H_

// ---------------------------------------------------------------------------
// Memory dimensions
// ---------------------------------------------------------------------------
`define COL     16          // Data/instruction word width (bits)
`define ROW_I   16          // Instruction memory depth (words, 16 x 16-bit)
`define ROW_D    8          // Data memory depth (words,  8 x 16-bit)

// ---------------------------------------------------------------------------
// Simulation control
// Increase SIM_TIME if your test program needs more clock cycles to complete.
// At 10 ns per clock (100 MHz) each #10 is one half-period; 320 ns = 16 cycles.
// ---------------------------------------------------------------------------
`define SIM_TIME #640      // 640 - 100000 Total simulation time for integration testbench

// ---------------------------------------------------------------------------
// Output file for data-memory dump (used in DataMemory.v $fmonitor)
// ---------------------------------------------------------------------------
`define DMEM_LOG  "./waves/dmem_log.txt"

`endif  // PARAMETER_H_

src/GPR.v
// =========================================================================
// Practical 4: StarCore-1 — Single-Cycle Processor in Verilog
// =========================================================================
//
// GROUP NUMBER:
//
// MEMBERS:
//   - Member 1 Michael Lighton, LGHMIC003
//   - Member 2 Glen Jones, JNSGLE007

// File        : GPR.v
// Description : General Purpose Register File.
//               8 registers, each 16 bits wide (R0–R7).
//               Two asynchronous (combinational) read ports.
//               One synchronous (clocked, positive-edge) write port.
//
// Task 2 — Student Implementation Required
// =============================================================================

`timescale 1ns / 1ps
`include "../src/Parameter.v"

module GPR (
    input        clk,

    // --- Write port (synchronous) -------------------------------------------
    input        reg_write_en,          // Write enable; write occurs on posedge clk
    input  [2:0] reg_write_dest,        // Destination register address (0–7)
    input  [15:0] reg_write_data,       // Data to write

    // --- Read port 1 (asynchronous) ------------------------------------------
    input  [2:0] reg_read_addr_1,       // Source register 1 address (RS1)
    output [15:0] reg_read_data_1,      // Data from RS1 — available immediately

    // --- Read port 2 (asynchronous) ------------------------------------------
    input  [2:0] reg_read_addr_2,       // Source register 2 address (RS2 / WS for I-type)
    output [15:0] reg_read_data_2       // Data from RS2 — available immediately
);

    // -------------------------------------------------------------------------
    // TODO: Declare the internal register array.
    //       You need an array of 8 registers, each 16 bits wide.
    //
    //       reg [15:0] reg_array [7:0];
    // -------------------------------------------------------------------------
    reg [15:0] reg_array [7:0]; // 8 registers, each 16 bits wide


    // -------------------------------------------------------------------------
    // TODO: Initialise all registers to zero at simulation start.
    //       Use an initial block with a for loop.
    //
    //       integer i;
    //       initial begin
    //           for (i = 0; i < 8; i = i + 1)
    //               reg_array[i] <= 16'd0;
    //       end
    // -------------------------------------------------------------------------
    integer i; // Loop variable for initialization
    initial begin // Initialize all registers to zero at simulation start
    for (i = 0; i < 8; i = i + 1) // Loop through all 8 registers
        reg_array[i] <= 16'd0; // Set each register to 0 (16-bit wide)
    end


    // -------------------------------------------------------------------------
    // TODO: Implement the synchronous write port.
    //       Write reg_write_data to reg_array[reg_write_dest] on the rising
    //       clock edge, but only when reg_write_en is asserted.
    //
    //       Use: always @(posedge clk) begin
    //                if (reg_write_en)
    //                    reg_array[...] <= ...;
    //            end
    //
    //       IMPORTANT: Use non-blocking assignment (<=) here.
    //                  This models a real flip-flop-based register.
    // -------------------------------------------------------------------------
    always @(posedge clk) begin // Synchronous write port
        if (reg_write_en) // Check if write enable is asserted
            reg_array[reg_write_dest] <= reg_write_data; // Write data to the specified register
    end


    // -------------------------------------------------------------------------
    // TODO: Implement the two asynchronous read ports.
    //       Both outputs must be continuous (combinational) assignments.
    //       They must update immediately whenever the address inputs change.
    //
    //       assign reg_read_data_1 = reg_array[reg_read_addr_1];
    //       assign reg_read_data_2 = reg_array[reg_read_addr_2];
    //
    //       NOTE: Because reads are asynchronous and the write is synchronous,
    //       if reg_read_addr_1 == reg_write_dest when reg_write_en is high,
    //       the read port returns the OLD value (before the write commits).
    //       Document this write-before-read behaviour in your report.
    // -------------------------------------------------------------------------
    assign reg_read_data_1 = reg_array[reg_read_addr_1]; // Asynchronous read port 1
    assign reg_read_data_2 = reg_array[reg_read_addr_2]; // Asynchronous read port 2


endmodule

tb/GPR_tb.v
// =============================================================================
// EEE4120F Practical 4 — StarCore-1 Processor
// File        : GPR_tb.v
// Description : Testbench for the General Purpose Register File (Task 2).
//               Verifies synchronous write and asynchronous read behaviour
//               for all 8 registers, plus edge cases.
//
// Run:
//   iverilog -Wall -I ../src -o ../build/gpr_sim ../src/GPR.v GPR_tb.v
//   cd ../test && ../build/gpr_sim
//   gtkwave ../waves/gpr_tb.vcd &
// =============================================================================

`timescale 1ns / 1ps
`include "../src/Parameter.v"

module GPR_tb;

    // -------------------------------------------------------------------------
    // DUT port connections
    // -------------------------------------------------------------------------
    reg        clk;
    reg        reg_write_en;
    reg  [2:0] reg_write_dest;
    reg  [15:0] reg_write_data;
    reg  [2:0] reg_read_addr_1;
    reg  [2:0] reg_read_addr_2;
    wire [15:0] reg_read_data_1;
    wire [15:0] reg_read_data_2;

    // -------------------------------------------------------------------------
    // DUT instantiation
    // -------------------------------------------------------------------------
    GPR uut (
        .clk              (clk),
        .reg_write_en     (reg_write_en),
        .reg_write_dest   (reg_write_dest),
        .reg_write_data   (reg_write_data),
        .reg_read_addr_1  (reg_read_addr_1),
        .reg_read_data_1  (reg_read_data_1),
        .reg_read_addr_2  (reg_read_addr_2),
        .reg_read_data_2  (reg_read_data_2)
    );

    // -------------------------------------------------------------------------
    // Clock generation — 10 ns period (100 MHz)
    // -------------------------------------------------------------------------
    initial clk = 1'b0;
    always  #5 clk = ~clk;

    // -------------------------------------------------------------------------
    // Waveform dump
    // -------------------------------------------------------------------------
    initial begin
        $dumpfile("../waves/gpr_tb.vcd");
        $dumpvars(0, GPR_tb);
    end

    // -------------------------------------------------------------------------
    // Failure counter
    // -------------------------------------------------------------------------
    integer fail_count;
    integer test_id;
    integer i;

    initial begin
        fail_count = 0;
        test_id    = 1;
    end

    task check16;
        input [15:0] got;
        input [15:0] expected;
        input [63:0] id;
        begin
            if (got !== expected) begin
                $display("FAIL [T%0d]: got = 0x%h, expected = 0x%h", id, got, expected);
                fail_count = fail_count + 1;
            end else
                $display("PASS [T%0d]: value = 0x%h", id, got);
        end
    endtask

    // =========================================================================
    // STIMULUS AND CHECKING
    // =========================================================================
    initial begin
        $display("=== GPR Testbench ===");

        // Initialise control signals
        reg_write_en   = 1'b0;
        reg_write_dest = 3'd0;
        reg_write_data = 16'd0;
        reg_read_addr_1 = 3'd0;
        reg_read_addr_2 = 3'd0;

        // Wait one clock cycle for GPR to initialise
        @(posedge clk); #1;

        // ------------------------------------------------------------------
        // TEST GROUP 1: Write a unique value to every register and read back
        // ------------------------------------------------------------------
        $display("--- Test Group 1: Write and read back all 8 registers ---");

        // TODO: For each register R0–R7, perform a synchronous write followed
        //       by an asynchronous read and verify the value.
        //
        //       Use a loop or individual test cases. Example for R0:
        //
        //           reg_write_en   = 1'b1;
        //           reg_write_dest = 3'd0;
        //           reg_write_data = 16'hA000;     // unique value for R0
        //           @(posedge clk); #1;             // commit the write
        //           reg_write_en   = 1'b0;
        //
        //           reg_read_addr_1 = 3'd0; #2;    // asynchronous read settles
        //           check16(reg_read_data_1, 16'hA000, test_id);
        //           test_id = test_id + 1;
        //
        //       Suggested values: R0=0xA000, R1=0xB001, R2=0xC002, R3=0xD003,
        //                         R4=0xE004, R5=0xF005, R6=0x1006, R7=0x2007



        for (i = 0; i < 8; i = i + 1) begin
            reg_write_en = 1'b1;
            reg_write_dest = i[2:0];    // loop index for destination address. 
            // i[2:0], i is typ 32 bits long, only need first 3 bits to represent 0-7.
           
            // Using index to get correct pattern:
            case(i)
                3'd0: reg_write_data = 16'hA000;
                3'd1: reg_write_data = 16'hB001;
                3'd2: reg_write_data = 16'hC002;
                3'd3: reg_write_data = 16'hD003;
                3'd4: reg_write_data = 16'hE004;
                3'd5: reg_write_data = 16'hF005;
                3'd6: reg_write_data = 16'h1006;
                3'd7: reg_write_data = 16'h2007;
            endcase


            @(posedge clk); #1;             // commit the write 
            reg_write_en   = 1'b0;          // Deasert write enable

            reg_read_addr_1 = i[2:0];       // asynchronous read settles
            #2;   

            // Verify
            check16(reg_read_data_1, reg_write_data, test_id);  // Use same reg write data to check
            test_id = test_id + 1;

        end
        // ------------------------------------------------------------------
        // TEST GROUP 2: Write with reg_write_en = 0 must NOT change register
        // ------------------------------------------------------------------
        $display("--- Test Group 2: Disabled write must not modify register ---");

        // TODO: Attempt to write a different value to R0 with reg_write_en=0.
        //       Read back R0 and confirm it still holds its original value.
        //
        //           reg_write_en   = 1'b0;
        //           reg_write_dest = 3'd0;
        //           reg_write_data = 16'hDEAD;     // this value must NOT be written
        //           @(posedge clk); #1;
        //
        //           reg_read_addr_1 = 3'd0; #2;
        //           check16(reg_read_data_1, 16'hA000, test_id);  // original value
        //           test_id = test_id + 1;

        reg_write_en = 1'b0;    // Not enabled
        reg_write_dest = 3'd0;  
        reg_write_data = 16'hDEAD;  // Wont be written
        reg_read_addr_1 = 3'd0;
        #2;
        check16(reg_read_data_1, 16'hA000, test_id);   
        test_id = test_id + 1; 


        // ------------------------------------------------------------------
        // TEST GROUP 3: Simultaneous read from two different registers
        // ------------------------------------------------------------------
        $display("--- Test Group 3: Simultaneous dual-port read ---");

        // TODO: Set reg_read_addr_1 and reg_read_addr_2 to two different
        //       registers and verify both values are correct simultaneously.
        //
        //           reg_read_addr_1 = 3'd1; // R1
        //           reg_read_addr_2 = 3'd3; // R3
        //           #2;
        //           check16(reg_read_data_1, 16'hB001, test_id); test_id=test_id+1;
        //           check16(reg_read_data_2, 16'hD003, test_id); test_id=test_id+1;

        reg_read_addr_1 = 3'd1; // R1
        reg_read_addr_2 = 3'd3; // R3
        #2;
        check16(reg_read_data_1, 16'hB001, test_id); test_id=test_id+1;
        check16(reg_read_data_2, 16'hD003, test_id); test_id=test_id+1;

        // ------------------------------------------------------------------
        // TEST GROUP 4: Read during write (write-before-read behaviour)
        // ------------------------------------------------------------------
        $display("--- Test Group 4: Read address matches write address during write ---");

        // TODO: Assert reg_write_en, set write and read addresses to the same
        //       register, and observe what reg_read_data_1 returns before
        //       the clock edge commits the write.
        //       Document in your report whether you see the old or new value.
        //
        //           reg_write_en   = 1'b1;
        //           reg_write_dest = 3'd2;
        //           reg_write_data = 16'hNEW_VALUE;
        //           reg_read_addr_1 = 3'd2;         // same as write dest
        //           #2;   // before clock edge
        //           $display("INFO [T%0d]: Read during write = 0x%h (document this)",
        //                    test_id, reg_read_data_1);
        //           test_id = test_id + 1;
        //           @(posedge clk); #1;
        //           reg_write_en = 1'b0;
        //           #2;
        //           check16(reg_read_data_1, 16'hNEW_VALUE, test_id); // after write
        //           test_id = test_id + 1;

        // Preparing for
        reg_write_en   = 1'b1;  
        reg_write_dest = 3'd2;
        reg_write_data = 16'hB00B;  // lol - data to be written

        // set read address simultaneously (same reg)
        reg_read_addr_1 = 3'd2;         // same as write dest

        // Wait for combinational logic to end before clock edge. write hasnt happened so checking if read port 'sees through' to write_data or shows old curr value
        #2;   // before clock edge
        $display("INFO [T%0d]: Read during write = 0x%h (document this)",
        test_id, reg_read_data_1);

        test_id = test_id + 1;

        // Trigger clock edg eto commit write to memory
        @(posedge clk);
        #1;
        reg_write_en = 1'b0;

        // Verify that the clock has passed and must be new value
        #2;
        check16(reg_read_data_1, 16'hB00B, test_id); // after write
        test_id = test_id + 1;

        // ------------------------------------------------------------------
        // Summary
        // ------------------------------------------------------------------
        $display("");
        if (fail_count == 0)
            $display("=== ALL %0d TESTS PASSED ===", test_id - 1);
        else
            $display("=== %0d / %0d TESTS FAILED ===", fail_count, test_id - 1);

        $finish;
    end

endmodule

waves/gpr_tb.vcd
$date
	Wed Apr 22 11:20:21 2026
$end
$version
	Icarus Verilog
$end
$timescale
	1ps
$end
$scope module GPR_tb $end
$var wire 16 ! reg_read_data_2 [15:0] $end
$var wire 16 " reg_read_data_1 [15:0] $end
$var reg 1 # clk $end
$var reg 3 $ reg_read_addr_1 [2:0] $end
$var reg 3 % reg_read_addr_2 [2:0] $end
$var reg 16 & reg_write_data [15:0] $end
$var reg 3 ' reg_write_dest [2:0] $end
$var reg 1 ( reg_write_en $end
$var integer 32 ) fail_count [31:0] $end
$var integer 32 * i [31:0] $end
$var integer 32 + test_id [31:0] $end
$scope module uut $end
$var wire 1 # clk $end
$var wire 3 , reg_read_addr_1 [2:0] $end
$var wire 3 - reg_read_addr_2 [2:0] $end
$var wire 16 . reg_read_data_1 [15:0] $end
$var wire 16 / reg_read_data_2 [15:0] $end
$var wire 16 0 reg_write_data [15:0] $end
$var wire 3 1 reg_write_dest [2:0] $end
$var wire 1 ( reg_write_en $end
$var integer 32 2 i [31:0] $end
$upscope $end
$scope task check16 $end
$var reg 16 3 expected [15:0] $end
$var reg 16 4 got [15:0] $end
$var reg 64 5 id [63:0] $end
$upscope $end
$upscope $end
$enddefinitions $end
$comment Show the parameter values. $end
$dumpall
$end
#0
$dumpvars
bx 5
bx 4
bx 3
b1000 2
b0 1
b0 0
b0 /
b0 .
b0 -
b0 ,
b1 +
bx *
b0 )
0(
b0 '
b0 &
b0 %
b0 $
0#
b0 "
b0 !
$end
#5000
1#
#6000
b1010000000000000 &
b1010000000000000 0
1(
b0 *
#10000
0#
#15000
b1010000000000000 "
b1010000000000000 .
b1010000000000000 !
b1010000000000000 /
1#
#16000
0(
#18000
b1011000000000001 &
b1011000000000001 0
b1 '
b1 1
1(
b1 *
b10 +
b1 5
b1010000000000000 3
b1010000000000000 4
#20000
0#
#25000
1#
#26000
b1011000000000001 "
b1011000000000001 .
b1 $
b1 ,
0(
#28000
b1100000000000010 &
b1100000000000010 0
b10 '
b10 1
1(
b10 *
b11 +
b10 5
b1011000000000001 3
b1011000000000001 4
#30000
0#
#35000
1#
#36000
b1100000000000010 "
b1100000000000010 .
b10 $
b10 ,
0(
#38000
b1101000000000011 &
b1101000000000011 0
b11 '
b11 1
1(
b11 *
b100 +
b11 5
b1100000000000010 3
b1100000000000010 4
#40000
0#
#45000
1#
#46000
b1101000000000011 "
b1101000000000011 .
b11 $
b11 ,
0(
#48000
b1110000000000100 &
b1110000000000100 0
b100 '
b100 1
1(
b100 *
b101 +
b100 5
b1101000000000011 3
b1101000000000011 4
#50000
0#
#55000
1#
#56000
b1110000000000100 "
b1110000000000100 .
b100 $
b100 ,
0(
#58000
b1111000000000101 &
b1111000000000101 0
b101 '
b101 1
1(
b101 *
b110 +
b101 5
b1110000000000100 3
b1110000000000100 4
#60000
0#
#65000
1#
#66000
b1111000000000101 "
b1111000000000101 .
b101 $
b101 ,
0(
#68000
b1000000000110 &
b1000000000110 0
b110 '
b110 1
1(
b110 *
b111 +
b110 5
b1111000000000101 3
b1111000000000101 4
#70000
0#
#75000
1#
#76000
b1000000000110 "
b1000000000110 .
b110 $
b110 ,
0(
#78000
b10000000000111 &
b10000000000111 0
b111 '
b111 1
1(
b111 *
b1000 +
b111 5
b1000000000110 3
b1000000000110 4
#80000
0#
#85000
1#
#86000
b10000000000111 "
b10000000000111 .
b111 $
b111 ,
0(
#88000
b1010000000000000 "
b1010000000000000 .
b0 $
b0 ,
b1101111010101101 &
b1101111010101101 0
b0 '
b0 1
b1000 *
b1001 +
b1000 5
b10000000000111 3
b10000000000111 4
#90000
b1101000000000011 !
b1101000000000011 /
b1011000000000001 "
b1011000000000001 .
b11 %
b11 -
b1 $
b1 ,
b1010 +
b1001 5
b1010000000000000 3
b1010000000000000 4
0#
#92000
b1100000000000010 "
b1100000000000010 .
b10 $
b10 ,
b1011000000001011 &
b1011000000001011 0
b10 '
b10 1
1(
b1100 +
b1011 5
b1101000000000011 3
b1101000000000011 4
#94000
b1101 +
#95000
b1011000000001011 "
b1011000000001011 .
1#
#96000
0(
#98000
b1110 +
b1101 5
b1011000000001011 3
b1011000000001011 4
